chromaconsole/Color.py
chromaconsole/ColorBackground.py
chromaconsole/ColorText.py
chromaconsole/Color_Background.py
chromaconsole/Color_Text.py
chromaconsole/Console.py
chromaconsole/Style.py
chromaconsole/__init__.py
chromaconsole/__main__.py
chromaconsole/chromaconsole.py
chromaconsole/styling.py
chromaconsole-0.8.6.3.dist-info/LICENSE.txt
chromaconsole-0.8.6.3.dist-info/METADATA
chromaconsole-0.8.6.3.dist-info/WHEEL
chromaconsole-0.8.6.3.dist-info/top_level.txt
chromaconsole-0.8.6.3.dist-info/RECORD
