Metadata-Version: 2.1
Name: chromaconsole
Version: 0.8.6.3
Summary: A small colorful module to change text colors in terminal
Author-email: Umit Tasdelen <umittadelen1277@gmail.com>
Project-URL: Homepage, https://github.com/umittadelen/chromaconsole
Project-URL: Bug_Tracker, https://github.com/umittadelen/chromaconsole/issues
Keywords: color,console,terminal,text,style
Classifier: Programming Language :: Python :: 3
Classifier: Programming Language :: Python :: 3.6
Classifier: Programming Language :: Python :: 3.7
Classifier: Programming Language :: Python :: 3.8
Classifier: Programming Language :: Python :: 3.9
Classifier: Programming Language :: Python :: 3.10
Classifier: Programming Language :: Python :: 3.11
Classifier: Programming Language :: Python :: 3.12
Classifier: License :: OSI Approved :: MIT License
Classifier: Operating System :: OS Independent
Requires-Python: >=3
License-File: LICENSE.txt
